deduce/__init__.py
deduce/annotation_processor.py
deduce/annotator.py
deduce/base_config.json
deduce/data/__init__.py
deduce/data/lookup/cache/__init__.py
deduce/data/lookup/src/__init__.py
deduce/data/lookup/src/institutions/lst_healthcare_institution/exceptions.txt
deduce/data/lookup/src/institutions/lst_healthcare_institution/items.txt
deduce/data/lookup/src/institutions/lst_healthcare_institution/transform.json
deduce/data/lookup/src/institutions/lst_hospital/items.txt
deduce/data/lookup/src/institutions/lst_hospital/transform.json
deduce/data/lookup/src/institutions/lst_hospital_abbr/items.txt
deduce/data/lookup/src/locations/lst_placename/lst_municipality/items.txt
deduce/data/lookup/src/locations/lst_placename/lst_province/items.txt
deduce/data/lookup/src/locations/lst_placename/lst_region/items.txt
deduce/data/lookup/src/locations/lst_placename/lst_residence/exceptions.txt
deduce/data/lookup/src/locations/lst_placename/lst_residence/items.txt
deduce/data/lookup/src/locations/lst_placename/transform.json
deduce/data/lookup/src/locations/lst_street/exceptions.txt
deduce/data/lookup/src/locations/lst_street/items.txt
deduce/data/lookup/src/locations/lst_street/streets_bag.txt
deduce/data/lookup/src/locations/lst_street/transform.json
deduce/data/lookup/src/names/lst_first_name/exceptions.txt
deduce/data/lookup/src/names/lst_first_name/items.txt
deduce/data/lookup/src/names/lst_initial/items.txt
deduce/data/lookup/src/names/lst_interfix/items.txt
deduce/data/lookup/src/names/lst_interfix_surname/exceptions.txt
deduce/data/lookup/src/names/lst_interfix_surname/items.txt
deduce/data/lookup/src/names/lst_prefix/items.txt
deduce/data/lookup/src/names/lst_surname/exceptions.txt
deduce/data/lookup/src/names/lst_surname/items.txt
deduce/data/lookup/src/whitelist/lst_common_word/exceptions.txt
deduce/data/lookup/src/whitelist/lst_common_word/items.txt
deduce/data/lookup/src/whitelist/lst_eponymous_disease/items.txt
deduce-3.0.6.dist-info/LICENSE.md
deduce-3.0.6.dist-info/METADATA
deduce-3.0.6.dist-info/WHEEL
deduce-3.0.6.dist-info/RECORD
