Metadata-Version: 2.3
Name: deduce
Version: 3.0.6
Summary: Deduce: de-identification method for Dutch medical text
License: LGPL-3.0-or-later
Keywords: de-identification,clinical text,dutch,nlp
Author: Vincent Menger
Author-email: vmenger@protonmail.com
Maintainer: Vincent Menger
Maintainer-email: vmenger@protonmail.com
Requires-Python: >=3.9,<4.0
Classifier: License :: OSI Approved :: GNU Lesser General Public License v3 (LGPLv3)
Classifier: License :: OSI Approved :: GNU Lesser General Public License v3 or later (LGPLv3+)
Classifier: Programming Language :: Python
Classifier: Programming Language :: Python :: 3
Classifier: Programming Language :: Python :: 3.9
Classifier: Programming Language :: Python :: 3.10
Classifier: Programming Language :: Python :: 3.11
Classifier: Programming Language :: Python :: 3.12
Classifier: Programming Language :: Python :: 3.13
Classifier: Topic :: Software Development :: Libraries :: Python Modules
Classifier: Topic :: Software Development :: Pre-processors
Classifier: Topic :: Text Processing
Classifier: Topic :: Text Processing :: Linguistic
Requires-Dist: docdeid (==1.0.1)
Requires-Dist: frozendict (>=2.4.6,<3.0.0)
Requires-Dist: rapidfuzz (>=3.13.0,<4.0.0)
Requires-Dist: regex (>=2024.11.6,<2025.0.0)
Project-URL: Repository, https://github.com/vmenger/deduce/
